icenet/__init__.py
icenet/exceptions.py
icenet/utils.py
icenet/data/__init__.py
icenet/data/cli.py
icenet/data/dataset.py
icenet/data/loader.py
icenet/data/process.py
icenet/data/producers.py
icenet/data/utils.py
icenet/data/datasets/__init__.py
icenet/data/datasets/utils.py
icenet/data/interfaces/__init__.py
icenet/data/interfaces/cds.py
icenet/data/interfaces/cmems.py
icenet/data/interfaces/downloader.py
icenet/data/interfaces/esgf.py
icenet/data/interfaces/mars.py
icenet/data/interfaces/utils.py
icenet/data/loaders/__init__.py
icenet/data/loaders/base.py
icenet/data/loaders/dask.py
icenet/data/loaders/stdlib.py
icenet/data/loaders/utils.py
icenet/data/processors/__init__.py
icenet/data/processors/cmip.py
icenet/data/processors/era5.py
icenet/data/processors/hres.py
icenet/data/processors/meta.py
icenet/data/processors/oras5.py
icenet/data/processors/osi.py
icenet/data/processors/utils.py
icenet/data/sic/__init__.py
icenet/data/sic/mask.py
icenet/data/sic/osisaf.py
icenet/data/sic/utils.py
icenet/model/__init__.py
icenet/model/callbacks.py
icenet/model/losses.py
icenet/model/metrics.py
icenet/model/models.py
icenet/model/predict.py
icenet/model/train.py
icenet/model/utils.py
icenet/plotting/__init__.py
icenet/plotting/data.py
icenet/plotting/forecast.py
icenet/plotting/trend.py
icenet/plotting/utils.py
icenet/plotting/video.py
icenet/process/__init__.py
icenet/process/azure.py
icenet/process/forecasts.py
icenet/process/local.py
icenet/process/predict.py
icenet/process/train.py
icenet/process/utils.py
icenet/results/__init__.py
icenet/results/metrics.py
icenet/results/threshold.py
icenet/tests/__init__.py
icenet/tests/test_entry_points.py
icenet/tests/test_mod.py
icenet-0.2.9.dist-info/LICENSE
icenet-0.2.9.dist-info/METADATA
icenet-0.2.9.dist-info/WHEEL
icenet-0.2.9.dist-info/entry_points.txt
icenet-0.2.9.dist-info/top_level.txt
icenet-0.2.9.dist-info/RECORD
