Metadata-Version: 2.2
Name: icenet
Version: 0.2.9
Summary: Library for operational IceNet forecasting
Home-page: https://github.com/icenet-ai
Author: British Antarctic Survey / Alan Turing Institute
Author-email: jambyr@bas.ac.uk
Classifier: Development Status :: 3 - Alpha
Classifier: Environment :: Console
Classifier: Intended Audience :: Science/Research
Classifier: License :: OSI Approved :: MIT License
Classifier: Natural Language :: English
Classifier: Operating System :: POSIX
Classifier: Programming Language :: Python :: 3
Classifier: Programming Language :: Python :: 3.9
Classifier: Programming Language :: Python :: 3.10
Classifier: Programming Language :: Python :: 3.11
Requires-Python: >=3.9, <3.12
License-File: LICENSE
Requires-Dist: azure-storage-blob
Requires-Dist: cartopy
Requires-Dist: cdsapi
Requires-Dist: cfgrib
Requires-Dist: copernicusmarine
Requires-Dist: dask
Requires-Dist: distributed
Requires-Dist: eccodes<2.39.0,>=2.37.0
Requires-Dist: ecmwf-api-client
Requires-Dist: h5py>2.10
Requires-Dist: ibicus
Requires-Dist: imageio-ffmpeg
Requires-Dist: matplotlib
Requires-Dist: motuclient
Requires-Dist: netcdf4<1.6.1
Requires-Dist: pandas
Requires-Dist: plotly
Requires-Dist: pip
Requires-Dist: pydap
Requires-Dist: rioxarray
Requires-Dist: scitools-iris
Requires-Dist: seaborn
Requires-Dist: setuptools
Requires-Dist: tensorboard
Requires-Dist: tensorflow<2.16
Requires-Dist: tensorflow-probability
Requires-Dist: wheel
Requires-Dist: xarray[io]
Provides-Extra: dev
Requires-Dist: black; extra == "dev"
Requires-Dist: build; extra == "dev"
Requires-Dist: coverage; extra == "dev"
Requires-Dist: flake8; extra == "dev"
Requires-Dist: importlib_metadata; extra == "dev"
Requires-Dist: pre-commit; extra == "dev"
Requires-Dist: pylint; extra == "dev"
Requires-Dist: pytest; extra == "dev"
Requires-Dist: ruff; extra == "dev"
Requires-Dist: tox; extra == "dev"
Requires-Dist: twine; extra == "dev"
Requires-Dist: watchdog; extra == "dev"
Requires-Dist: yapf; extra == "dev"
Provides-Extra: docs
Requires-Dist: jinja2>=3.1.3; extra == "docs"
Requires-Dist: linkify-it-py; extra == "docs"
Requires-Dist: myst-nb; extra == "docs"
Requires-Dist: myst_parser; extra == "docs"
Requires-Dist: pylint; extra == "docs"
Requires-Dist: Sphinx; extra == "docs"
Requires-Dist: sphinx-book-theme; extra == "docs"
Requires-Dist: sphinx_design; extra == "docs"
Requires-Dist: sphinx-multiversion; extra == "docs"
Requires-Dist: sphinxcontrib-kroki; extra == "docs"
Dynamic: author
Dynamic: author-email
Dynamic: classifier
Dynamic: description
Dynamic: description-content-type
Dynamic: home-page
Dynamic: keywords
Dynamic: provides-extra
Dynamic: requires-dist
Dynamic: requires-python
Dynamic: summary
